MANIFEST.in
README.md
setup.py
zohodocs/__init__.py
zohodocs/core.py
zohodocs.egg-info/PKG-INFO
zohodocs.egg-info/SOURCES.txt
zohodocs.egg-info/dependency_links.txt
zohodocs.egg-info/requires.txt
zohodocs.egg-info/top_level.txt