Metadata-Version: 1.0
Name: zohodocs
Version: 0.1.0
Summary: 
